<?xml version="1.0" encoding="UTF-8" standalone="no"?><boxscore xmlns="http://feed.elasticstats.com/schema/rugby/v1/matches-boxscore.xsd" generated="2017-08-13T13:20:27Z">
  <matches>
    <match coverage="2" id="092f71ec-3466-4aa6-9e0f-cfb35d4f0d24" period="" scheduled="2016-01-01T14:00:00Z" status="closed">
      <league id="92828466-f9d7-47d8-bc0a-3c97e6a91ee8" name="Rugby Union"/>
      <tournament id="72164de2-c2cd-42d8-8596-66bcf45d4170" name="Pro 12"/>
      <season end="2016-06-05T21:59:59Z" id="ea65afbf-a4f0-447a-8ef7-b285125507a9" name="Pro 12 15/16" start="2015-09-03T22:00:00Z" year="2015"/>
      <home alias="OSP" id="48daa401-0492-4b07-bcf7-95fc5dbfe15d" name="Ospreys" score="12">
        <scoring>
          <period number="1" points="12"/>
          <period number="2" points="0"/>
        </scoring>
      </home>
      <away alias="NPT" id="ae72c0f6-9103-422c-bff7-102cdfbef3e6" name="NG Dragons" score="7">
        <scoring>
          <period number="1" points="0"/>
          <period number="2" points="7"/>
        </scoring>
      </away>
      <venue capacity="20827" city="Swansea" country="Wales" id="16073a24-5270-4691-b458-f5124db3decf" latitude="51.6422" longitude="-3.9351" name="Liberty Stadium"/>
    </match>
    <match coverage="2" id="82e9474a-a85c-4d6e-b9b4-d4ef633e6a06" period="" scheduled="2016-01-01T15:00:00Z" status="closed">
      <league id="92828466-f9d7-47d8-bc0a-3c97e6a91ee8" name="Rugby Union"/>
      <tournament id="6db01793-299d-4283-930f-35c2f796fee4" name="English Premiership"/>
      <season end="2016-05-31T21:59:59Z" id="3a380038-6536-4b85-a3e1-b6f328bd3002" name="English Premiership 15/16" start="2015-10-15T22:00:00Z" year="2015"/>
      <home alias="NHA" id="2e31b0db-cbad-4580-9adb-8a92f586cb17" name="Northampton" score="8">
        <scoring>
          <period number="1" points="8"/>
          <period number="2" points="0"/>
        </scoring>
      </home>
      <away alias="EXE" id="9d1f2e01-e5a3-44cd-8e2c-859a97165f1b" name="Exeter" score="3">
        <scoring>
          <period number="1" points="0"/>
          <period number="2" points="3"/>
        </scoring>
      </away>
      <venue city="Northampton" country="England" id="810790ca-76d1-47cf-a627-a1e701537253" latitude="52.239444" longitude="-0.919722" name="Franklin's Gardens"/>
    </match>
    <match coverage="2" id="685fd6ef-dfdc-4c96-82fa-b46529a86314" period="" scheduled="2016-01-01T17:00:00Z" status="closed">
      <league id="92828466-f9d7-47d8-bc0a-3c97e6a91ee8" name="Rugby Union"/>
      <tournament id="72164de2-c2cd-42d8-8596-66bcf45d4170" name="Pro 12"/>
      <season end="2016-06-05T21:59:59Z" id="ea65afbf-a4f0-447a-8ef7-b285125507a9" name="Pro 12 15/16" start="2015-09-03T22:00:00Z" year="2015"/>
      <home alias="LEI" id="5a9ba058-9918-42fd-b077-e9cae0c47f78" name="Leinster" score="13">
        <scoring>
          <period number="1" points="3"/>
          <period number="2" points="10"/>
        </scoring>
      </home>
      <away alias="CON" id="8dc17c77-7e0e-4a84-bc57-b88d470836be" name="Connacht" score="0">
        <scoring>
          <period number="1" points="0"/>
          <period number="2" points="0"/>
        </scoring>
      </away>
      <venue city="Dublin" country="Ireland" id="e83f76b6-963d-44a7-9526-711de30a9206" latitude="53.325556" longitude="-6.229444" name="RDS"/>
    </match>
    <match coverage="2" id="a8815217-325e-4640-bf36-f20ab1c736d3" period="" scheduled="2016-01-01T17:00:00Z" status="closed">
      <league id="92828466-f9d7-47d8-bc0a-3c97e6a91ee8" name="Rugby Union"/>
      <tournament id="72164de2-c2cd-42d8-8596-66bcf45d4170" name="Pro 12"/>
      <season end="2016-06-05T21:59:59Z" id="ea65afbf-a4f0-447a-8ef7-b285125507a9" name="Pro 12 15/16" start="2015-09-03T22:00:00Z" year="2015"/>
      <home alias="CAR" id="6a6c61fb-060f-4973-8472-a50ef2770ce8" name="Cardiff" score="29">
        <scoring>
          <period number="1" points="10"/>
          <period number="2" points="19"/>
        </scoring>
      </home>
      <away alias="SCA" id="e3c0d780-460b-44cf-b126-d5dba29b2e51" name="Scarlets" score="27">
        <scoring>
          <period number="1" points="20"/>
          <period number="2" points="7"/>
        </scoring>
      </away>
      <venue city="Cardiff" country="Wales" id="da9cce70-3bf5-44f8-8f82-2aeff5e87754" latitude="51.479722" longitude="-3.183611" name="Cardiff Arms Park"/>
    </match>
  </matches>
</boxscore>